setup.py
distributions_arjun/Binomialdistribution.py
distributions_arjun/Gaussiandistribution.py
distributions_arjun/Generaldistribution.py
distributions_arjun/__init__.py
distributions_arjun.egg-info/PKG-INFO
distributions_arjun.egg-info/SOURCES.txt
distributions_arjun.egg-info/dependency_links.txt
distributions_arjun.egg-info/not-zip-safe
distributions_arjun.egg-info/top_level.txt